lsttrends/__init__.py
lsttrends/common.py
lsttrends/lsttrends.py
lsttrends-0.0.1.dist-info/licenses/LICENSE
lsttrends-0.0.1.dist-info/METADATA
lsttrends-0.0.1.dist-info/WHEEL
lsttrends-0.0.1.dist-info/entry_points.txt
lsttrends-0.0.1.dist-info/top_level.txt
lsttrends-0.0.1.dist-info/RECORD
